z3c/table/README.rst
z3c/table/__init__.py
z3c/table/batch.py
z3c/table/batch.rst
z3c/table/column.py
z3c/table/column.rst
z3c/table/configure.zcml
z3c/table/header.py
z3c/table/i18n.py
z3c/table/interfaces.py
z3c/table/miscellaneous.rst
z3c/table/sequence.rst
z3c/table/sort.rst
z3c/table/table.py
z3c/table/testing.py
z3c/table/tests.py
z3c/table/value.py
z3c_table-4.0.dist-info/licenses/LICENSE.txt
z3c_table-4.0.dist-info/METADATA
z3c_table-4.0.dist-info/WHEEL
z3c_table-4.0.dist-info/top_level.txt
z3c_table-4.0.dist-info/RECORD
