Metadata-Version: 2.4
Name: z3c.table
Version: 4.0
Summary: Modular table rendering implementation for Zope3
Home-page: https://github.com/zopefoundation/z3c.table
Author: Stephan Richter, Roger Ineichen and the Zope Community
Author-email: zope-dev@zope.dev
License: ZPL-2.1
Keywords: zope3 z3c table content provider
Classifier: Development Status :: 4 - Beta
Classifier: Environment :: Web Environment
Classifier: Intended Audience :: Developers
Classifier: License :: OSI Approved :: Zope Public License
Classifier: Programming Language :: Python
Classifier: Programming Language :: Python :: 3
Classifier: Programming Language :: Python :: 3.9
Classifier: Programming Language :: Python :: 3.10
Classifier: Programming Language :: Python :: 3.11
Classifier: Programming Language :: Python :: 3.12
Classifier: Programming Language :: Python :: 3.13
Classifier: Programming Language :: Python :: Implementation :: CPython
Classifier: Programming Language :: Python :: Implementation :: PyPy
Classifier: Natural Language :: English
Classifier: Operating System :: OS Independent
Classifier: Topic :: Internet :: WWW/HTTP
Classifier: Framework :: Zope :: 3
Requires-Python: >=3.9
License-File: LICENSE.txt
Requires-Dist: setuptools
Requires-Dist: future>=0.14.0
Requires-Dist: z3c.batching>=1.1.0
Requires-Dist: zope.component
Requires-Dist: zope.contentprovider
Requires-Dist: zope.dublincore
Requires-Dist: zope.i18nmessageid
Requires-Dist: zope.i18n
Requires-Dist: zope.interface
Requires-Dist: zope.location
Requires-Dist: zope.schema
Requires-Dist: zope.security
Requires-Dist: zope.traversing
Provides-Extra: test
Requires-Dist: zope.container; extra == "test"
Requires-Dist: zope.publisher; extra == "test"
Requires-Dist: zope.site; extra == "test"
Requires-Dist: zope.testing; extra == "test"
Requires-Dist: zope.testrunner; extra == "test"
Dynamic: author
Dynamic: author-email
Dynamic: classifier
Dynamic: description
Dynamic: home-page
Dynamic: keywords
Dynamic: license
Dynamic: license-file
Dynamic: provides-extra
Dynamic: requires-dist
Dynamic: requires-python
Dynamic: summary
